{
  "generator-jhipster": {
    "applicationType": "gateway",
    "gitCompany": "",
    "baseName": "jhipsterTestApp1GW",
    "packageName": "com.capgemini.ht",
    "packageFolder": "com/capgemini/ht",
    "serverPort": 7070,
    "serviceDiscoveryType": "eureka",
    "authenticationType": "jwt",
    "uaaBaseName": "../uaa",
    "cacheProvider": "ehcache",
    "enableHibernateCache": true,
    "websocket": false,
    "databaseType": "sql",
    "devDatabaseType": "h2Disk",
    "prodDatabaseType": "mysql",
    "searchEngine": false,
    "enableSwaggerCodegen": false,
    "messageBroker": false,
    "buildTool": "maven",
    "useSass": true,
    "clientPackageManager": "npm",
    "testFrameworks": ["protractor"],
    "enableTranslation": true,
    "nativeLanguage": "en",
    "languages": ["en"],
    "clientFramework": "angularX",
    "jhiPrefix": "jhi",
    "jhipsterVersion": "6.6.0",
    "jwtSecretKey": "YmI1ZDA1NjVlYTU0YjNmMjg5OTM4NGYyNWM4OWIzYjRiYzQwMGQ0M2NjZDBmN2VkMjE1OTQ3OWM4NzhlNTIyZWZlNDRhZjk5ZDRkODQ1Mjc3ZGRkODlhOGVkODBmNTk0MTExMTU3YWYwNTgyOTQyM2VlZWY5MGVhMWVjNzA3NWM=",
    "embeddableLaunchScript": false,
    "clientTheme": "none",
    "creationTimestamp": 1580307416566,
    "entitySuffix": "",
    "dtoSuffix": "DTO",
    "otherModules": [],
    "blueprints": []
  },
  "git-provider": "GitHub",
  "git-company": "rrugiero",
  "repository-name": "jhipster-test-app1-gw"
}
